rollouts/__init__.py
rollouts/cache.py
rollouts/client.py
rollouts/datatypes.py
rollouts/migrate.py
rollouts/openrouter.py
rollouts/py.typed
rollouts/rate_limiter.py
rollouts/think_handler.py
rollouts/types.py
rollouts-0.1.11.dist-info/licenses/LICENSE
rollouts-0.1.11.dist-info/METADATA
rollouts-0.1.11.dist-info/WHEEL
rollouts-0.1.11.dist-info/top_level.txt
rollouts-0.1.11.dist-info/RECORD
